{
    "Maps": [
        {"Easy":
            [
                {
                    "filename": "airport.jpg",
                    "width": 4360,
                    "height": 2762,
                    "waldoX": 1222,
                    "waldoY": 991,
                    "odlawX": 434,
                    "odlawY": 1823
                },
                {
                    "filename": "XDDD.jpg",
                    "width": 4360,
                    "height": 2762,
                    "waldoX": 1222,
                    "waldoY": 991,
                    "odlawX": 434,
                    "odlawY": 1823
                },
                {
                    "filename": "XDDD.jpg",
                    "width": 4360,
                    "height": 2762,
                    "waldoX": 1222,
                    "waldoY": 991,
                    "odlawX": 434,
                    "odlawY": 1823
                },
                {
                    "filename": "XDDD.jpg",
                    "width": 4360,
                    "height": 2762,
                    "waldoX": 1222,
                    "waldoY": 991,
                    "odlawX": 434,
                    "odlawY": 1823
                },
                {
                    "filename": "XDDD.jpg",
                    "width": 4360,
                    "height": 2762,
                    "waldoX": 1222,
                    "waldoY": 991,
                    "odlawX": 434,
                    "odlawY": 1823
                }
            ]

        },
        {"Medium":
            [
                {
                    "filename": "hollywood.jpeg",
                    "width": 3000,
                    "height": 1935,
                    "waldoX": 2096,
                    "waldoY": 823,
                    "odlawX": 1663,
                    "odlawY": 1541
                },
                {
                    "filename": "XDDD.jpg",
                    "width": 4360,
                    "height": 2762,
                    "waldoX": 1222,
                    "waldoY": 991,
                    "odlawX": 434,
                    "odlawY": 1823
                }

            ]
        },
        {"Hard":
        [
            {
                "filename": "fruit-mountain.jpeg",
                "width": 3000,
                "height": 1933,
                "waldoX": 2672,
                "waldoY": 1285,
                "odlawX": 1980,
                "odlawY": 1085
            }

        ]
    }
    ]
}